<?xml version="1.0" encoding="UTF-8"?><Root>
      		<SubSystem>
		<Name>AN2CAN_RPDOs</Name>
		<xPCName>SpeedgoatCANOpen07/AN2CAN_RPDOs</xPCName>
		
		
			  
			  
              <signal>
              <sigName>RPDOs from AN2CAN /p1</sigName>
              <xpcsigName>AN2CAN_RPDOs/RPDOs from AN2CAN /p1</xpcsigName>
              <sigWidth>1</sigWidth>
              <sigDim>[1, 1]</sigDim>
			  <SubSystemName>SpeedgoatCANOpen07/AN2CAN_RPDOs</SubSystemName>
                <sigLabel>Channel_AN1</sigLabel>
			  <sigTestPoint>false</sigTestPoint>
            </signal>
			  
			  
              <signal>
              <sigName>RPDOs from AN2CAN /p2</sigName>
              <xpcsigName>AN2CAN_RPDOs/RPDOs from AN2CAN /p2</xpcsigName>
              <sigWidth>1</sigWidth>
              <sigDim>[1, 1]</sigDim>
			  <SubSystemName>SpeedgoatCANOpen07/AN2CAN_RPDOs</SubSystemName>
                <sigLabel>Channel_AN2</sigLabel>
			  <sigTestPoint>false</sigTestPoint>
            </signal>
			  
			  
              <signal>
              <sigName>RPDOs from AN2CAN /p3</sigName>
              <xpcsigName>AN2CAN_RPDOs/RPDOs from AN2CAN /p3</xpcsigName>
              <sigWidth>1</sigWidth>
              <sigDim>[1, 1]</sigDim>
			  <SubSystemName>SpeedgoatCANOpen07/AN2CAN_RPDOs</SubSystemName>
                <sigLabel>Channel_AN3</sigLabel>
			  <sigTestPoint>false</sigTestPoint>
            </signal>
			  
			  
              <signal>
              <sigName>RPDOs from AN2CAN /p4</sigName>
              <xpcsigName>AN2CAN_RPDOs/RPDOs from AN2CAN /p4</xpcsigName>
              <sigWidth>1</sigWidth>
              <sigDim>[1, 1]</sigDim>
			  <SubSystemName>SpeedgoatCANOpen07/AN2CAN_RPDOs</SubSystemName>
                <sigLabel>Channel_AN4</sigLabel>
			  <sigTestPoint>false</sigTestPoint>
            </signal>

		</SubSystem>
		<SubSystem>
		<Name>APT_RPDOs</Name>
		<xPCName>SpeedgoatCANOpen07/APT_RPDOs</xPCName>
		
		
			  
			  
              <signal>
              <sigName>RPDOs from APT/p1</sigName>
              <xpcsigName>APT_RPDOs/RPDOs from APT/p1</xpcsigName>
              <sigWidth>1</sigWidth>
              <sigDim>[1, 1]</sigDim>
			  <SubSystemName>SpeedgoatCANOpen07/APT_RPDOs</SubSystemName>
                <sigLabel>APT_StatusWord</sigLabel>
			  <sigTestPoint>false</sigTestPoint>
            </signal>
			  
			  
              <signal>
              <sigName>RPDOs from APT/p2</sigName>
              <xpcsigName>APT_RPDOs/RPDOs from APT/p2</xpcsigName>
              <sigWidth>1</sigWidth>
              <sigDim>[1, 1]</sigDim>
			  <SubSystemName>SpeedgoatCANOpen07/APT_RPDOs</SubSystemName>
                <sigLabel>APT_PhaseCurrent</sigLabel>
			  <sigTestPoint>false</sigTestPoint>
            </signal>
			  
			  
              <signal>
              <sigName>RPDOs from APT/p3</sigName>
              <xpcsigName>APT_RPDOs/RPDOs from APT/p3</xpcsigName>
              <sigWidth>1</sigWidth>
              <sigDim>[1, 1]</sigDim>
			  <SubSystemName>SpeedgoatCANOpen07/APT_RPDOs</SubSystemName>
                <sigLabel>APT_Speed</sigLabel>
			  <sigTestPoint>false</sigTestPoint>
            </signal>
			  
			  
              <signal>
              <sigName>RPDOs from APT/p4</sigName>
              <xpcsigName>APT_RPDOs/RPDOs from APT/p4</xpcsigName>
              <sigWidth>1</sigWidth>
              <sigDim>[1, 1]</sigDim>
			  <SubSystemName>SpeedgoatCANOpen07/APT_RPDOs</SubSystemName>
                <sigLabel>APT_BusVoltage</sigLabel>
			  <sigTestPoint>false</sigTestPoint>
            </signal>
			  
			  
              <signal>
              <sigName>RPDOs from APT/p5</sigName>
              <xpcsigName>APT_RPDOs/RPDOs from APT/p5</xpcsigName>
              <sigWidth>1</sigWidth>
              <sigDim>[1, 1]</sigDim>
			  <SubSystemName>SpeedgoatCANOpen07/APT_RPDOs</SubSystemName>
                <sigLabel>APT_MotorTemp</sigLabel>
			  <sigTestPoint>false</sigTestPoint>
            </signal>
			  
			  
              <signal>
              <sigName>RPDOs from APT/p6</sigName>
              <xpcsigName>APT_RPDOs/RPDOs from APT/p6</xpcsigName>
              <sigWidth>1</sigWidth>
              <sigDim>[1, 1]</sigDim>
			  <SubSystemName>SpeedgoatCANOpen07/APT_RPDOs</SubSystemName>
                <sigLabel>APT_Temp</sigLabel>
			  <sigTestPoint>false</sigTestPoint>
            </signal>
			  
			  
              <signal>
              <sigName>RPDOs from APT/p7</sigName>
              <xpcsigName>APT_RPDOs/RPDOs from APT/p7</xpcsigName>
              <sigWidth>1</sigWidth>
              <sigDim>[1, 1]</sigDim>
			  <SubSystemName>SpeedgoatCANOpen07/APT_RPDOs</SubSystemName>
                <sigLabel>APT_ErrStatus</sigLabel>
			  <sigTestPoint>false</sigTestPoint>
            </signal>
			  
			  
              <signal>
              <sigName>RPDOs from APT/p8</sigName>
              <xpcsigName>APT_RPDOs/RPDOs from APT/p8</xpcsigName>
              <sigWidth>1</sigWidth>
              <sigDim>[1, 1]</sigDim>
			  <SubSystemName>SpeedgoatCANOpen07/APT_RPDOs</SubSystemName>
                <sigLabel>APT_Direction</sigLabel>
			  <sigTestPoint>false</sigTestPoint>
            </signal>

		</SubSystem>
		<SubSystem>
		<Name>Dunker #1</Name>
		<xPCName>SpeedgoatCANOpen07/Dunker #1</xPCName>
		
		
			  
			  
              <signal>
              <sigName>RPDOs from Dunker #1/p1</sigName>
              <xpcsigName>Dunker #1/RPDOs from Dunker #1/p1</xpcsigName>
              <sigWidth>1</sigWidth>
              <sigDim>[1, 1]</sigDim>
			  <SubSystemName>SpeedgoatCANOpen07/Dunker #1</SubSystemName>
                <sigLabel>DunkA_StatusWord</sigLabel>
			  <sigTestPoint>false</sigTestPoint>
            </signal>
			  
			  
              <signal>
              <sigName>RPDOs from Dunker #1/p2</sigName>
              <xpcsigName>Dunker #1/RPDOs from Dunker #1/p2</xpcsigName>
              <sigWidth>1</sigWidth>
              <sigDim>[1, 1]</sigDim>
			  <SubSystemName>SpeedgoatCANOpen07/Dunker #1</SubSystemName>
                <sigLabel>DunkA_OperationMode</sigLabel>
			  <sigTestPoint>false</sigTestPoint>
            </signal>
			  
			  
              <signal>
              <sigName>RPDOs from Dunker #1/p3</sigName>
              <xpcsigName>Dunker #1/RPDOs from Dunker #1/p3</xpcsigName>
              <sigWidth>1</sigWidth>
              <sigDim>[1, 1]</sigDim>
			  <SubSystemName>SpeedgoatCANOpen07/Dunker #1</SubSystemName>
                <sigLabel>DunkA_CurrentActualValue</sigLabel>
			  <sigTestPoint>false</sigTestPoint>
            </signal>
			  
			  
              <signal>
              <sigName>RPDOs from Dunker #1/p4</sigName>
              <xpcsigName>Dunker #1/RPDOs from Dunker #1/p4</xpcsigName>
              <sigWidth>1</sigWidth>
              <sigDim>[1, 1]</sigDim>
			  <SubSystemName>SpeedgoatCANOpen07/Dunker #1</SubSystemName>
                <sigLabel>DunkA_ActualTorque</sigLabel>
			  <sigTestPoint>false</sigTestPoint>
            </signal>
			  
			  
              <signal>
              <sigName>RPDOs from Dunker #1/p5</sigName>
              <xpcsigName>Dunker #1/RPDOs from Dunker #1/p5</xpcsigName>
              <sigWidth>1</sigWidth>
              <sigDim>[1, 1]</sigDim>
			  <SubSystemName>SpeedgoatCANOpen07/Dunker #1</SubSystemName>
                <sigLabel>DunkA_ActualPosition</sigLabel>
			  <sigTestPoint>false</sigTestPoint>
            </signal>
			  
			  
              <signal>
              <sigName>RPDOs from Dunker #1/p6</sigName>
              <xpcsigName>Dunker #1/RPDOs from Dunker #1/p6</xpcsigName>
              <sigWidth>1</sigWidth>
              <sigDim>[1, 1]</sigDim>
			  <SubSystemName>SpeedgoatCANOpen07/Dunker #1</SubSystemName>
                <sigLabel>DunkA_ActualVelocity</sigLabel>
			  <sigTestPoint>false</sigTestPoint>
            </signal>

		</SubSystem>
		<SubSystem>
		<Name>Joystick_RPDOs1</Name>
		<xPCName>SpeedgoatCANOpen07/Joystick_RPDOs1</xPCName>
		
		
			  
			  
              <signal>
              <sigName>RPDOs from Joystick/p1</sigName>
              <xpcsigName>Joystick_RPDOs1/RPDOs from Joystick/p1</xpcsigName>
              <sigWidth>1</sigWidth>
              <sigDim>[1, 1]</sigDim>
			  <SubSystemName>SpeedgoatCANOpen07/Joystick_RPDOs1</SubSystemName>
                <sigLabel>Joystick_ButtonsStatus</sigLabel>
			  <sigTestPoint>false</sigTestPoint>
            </signal>
			  
			  
              <signal>
              <sigName>RPDOs from Joystick/p2</sigName>
              <xpcsigName>Joystick_RPDOs1/RPDOs from Joystick/p2</xpcsigName>
              <sigWidth>1</sigWidth>
              <sigDim>[1, 1]</sigDim>
			  <SubSystemName>SpeedgoatCANOpen07/Joystick_RPDOs1</SubSystemName>
                <sigLabel>Joystick_LongCmd</sigLabel>
			  <sigTestPoint>false</sigTestPoint>
            </signal>
			  
			  
              <signal>
              <sigName>RPDOs from Joystick/p3</sigName>
              <xpcsigName>Joystick_RPDOs1/RPDOs from Joystick/p3</xpcsigName>
              <sigWidth>1</sigWidth>
              <sigDim>[1, 1]</sigDim>
			  <SubSystemName>SpeedgoatCANOpen07/Joystick_RPDOs1</SubSystemName>
                <sigLabel>Joystick_LatCmd</sigLabel>
			  <sigTestPoint>false</sigTestPoint>
            </signal>

		</SubSystem>
		<SubSystem>
		<Name>Speedgoat_TPDOs</Name>
		<xPCName>SpeedgoatCANOpen07/Speedgoat_TPDOs</xPCName>
				<SubSystem>
		<Name>CAN Bus Communication</Name>
		<xPCName>SpeedgoatCANOpen07/Speedgoat_TPDOs/CAN Bus Communication</xPCName>
				<SubSystem>
		<Name>CANOpen Slave 
Protocol Stack - CAN Bus #1 (A)</Name>
		<xPCName>SpeedgoatCANOpen07/Speedgoat_TPDOs/CAN Bus Communication/CANOpen Slave  Protocol Stack - CAN Bus #1 (A)</xPCName>
				<SubSystem>
		<Name>CAN RX Wrapper</Name>
		<xPCName>SpeedgoatCANOpen07/Speedgoat_TPDOs/CAN Bus Communication/CANOpen Slave  Protocol Stack - CAN Bus #1 (A)/CAN RX Wrapper</xPCName>
		
		
            <block>
            <blkName>CAN Read</blkName>
            <xpcblkName>Speedgoat_TPDOs/CAN Bus Communication/CANOpen Slave  Protocol Stack - CAN Bus #1 (A)/CAN RX Wrapper/CAN Read</xpcblkName>
            <SLblockPath>SpeedgoatCANOpen07/Speedgoat_TPDOs/CAN Bus Communication/CANOpen Slave  Protocol Stack - CAN Bus #1 (A)/CAN RX Wrapper/CAN Read</SLblockPath>
            <isSrc>[1 0 6]</isSrc>
          <parameter>
          <paramName>P1</paramName>
          <dim>[1, 6]</dim>  
		  <SubSystemName>SpeedgoatCANOpen07/Speedgoat_TPDOs/CAN Bus Communication/CANOpen Slave  Protocol Stack - CAN Bus #1 (A)/CAN RX Wrapper</SubSystemName>
          </parameter>
          </block>
            <block>
            <blkName>Switch</blkName>
            <xpcblkName>Speedgoat_TPDOs/CAN Bus Communication/CANOpen Slave  Protocol Stack - CAN Bus #1 (A)/CAN RX Wrapper/Switch</xpcblkName>
            <SLblockPath>SpeedgoatCANOpen07/Speedgoat_TPDOs/CAN Bus Communication/CANOpen Slave  Protocol Stack - CAN Bus #1 (A)/CAN RX Wrapper/Switch</SLblockPath>
            <isSrc>[0 3 1]</isSrc>
          <parameter>
          <paramName>Threshold</paramName>
          <dim>[1, 1]</dim>  
		  <SubSystemName>SpeedgoatCANOpen07/Speedgoat_TPDOs/CAN Bus Communication/CANOpen Slave  Protocol Stack - CAN Bus #1 (A)/CAN RX Wrapper</SubSystemName>
          </parameter>
          </block>
			  
			  
              <signal>
              <sigName>CAN Read/p1</sigName>
              <xpcsigName>Speedgoat_TPDOs/CAN Bus Communication/CANOpen Slave  Protocol Stack - CAN Bus #1 (A)/CAN RX Wrapper/CAN Read/p1</xpcsigName>
              <sigWidth>1</sigWidth>
              <sigDim>[1, 1]</sigDim>
			  <SubSystemName>SpeedgoatCANOpen07/Speedgoat_TPDOs/CAN Bus Communication/CANOpen Slave  Protocol Stack - CAN Bus #1 (A)/CAN RX Wrapper</SubSystemName>
			  <sigTestPoint>false</sigTestPoint>
            </signal>
			  
			  
              <signal>
              <sigName>CAN Read/p2</sigName>
              <xpcsigName>Speedgoat_TPDOs/CAN Bus Communication/CANOpen Slave  Protocol Stack - CAN Bus #1 (A)/CAN RX Wrapper/CAN Read/p2</xpcsigName>
              <sigWidth>1</sigWidth>
              <sigDim>[1, 1]</sigDim>
			  <SubSystemName>SpeedgoatCANOpen07/Speedgoat_TPDOs/CAN Bus Communication/CANOpen Slave  Protocol Stack - CAN Bus #1 (A)/CAN RX Wrapper</SubSystemName>
			  <sigTestPoint>false</sigTestPoint>
            </signal>
			  
			  
              <signal>
              <sigName>CAN Read/p3</sigName>
              <xpcsigName>Speedgoat_TPDOs/CAN Bus Communication/CANOpen Slave  Protocol Stack - CAN Bus #1 (A)/CAN RX Wrapper/CAN Read/p3</xpcsigName>
              <sigWidth>1</sigWidth>
              <sigDim>[1, 1]</sigDim>
			  <SubSystemName>SpeedgoatCANOpen07/Speedgoat_TPDOs/CAN Bus Communication/CANOpen Slave  Protocol Stack - CAN Bus #1 (A)/CAN RX Wrapper</SubSystemName>
			  <sigTestPoint>false</sigTestPoint>
            </signal>
			  
			  
              <signal>
              <sigName>CAN Read/p4</sigName>
              <xpcsigName>Speedgoat_TPDOs/CAN Bus Communication/CANOpen Slave  Protocol Stack - CAN Bus #1 (A)/CAN RX Wrapper/CAN Read/p4</xpcsigName>
              <sigWidth>1</sigWidth>
              <sigDim>[1, 1]</sigDim>
			  <SubSystemName>SpeedgoatCANOpen07/Speedgoat_TPDOs/CAN Bus Communication/CANOpen Slave  Protocol Stack - CAN Bus #1 (A)/CAN RX Wrapper</SubSystemName>
			  <sigTestPoint>false</sigTestPoint>
            </signal>
			  
			  
              <signal>
              <sigName>CAN Read/p5</sigName>
              <xpcsigName>Speedgoat_TPDOs/CAN Bus Communication/CANOpen Slave  Protocol Stack - CAN Bus #1 (A)/CAN RX Wrapper/CAN Read/p5</xpcsigName>
              <sigWidth>1</sigWidth>
              <sigDim>[1, 1]</sigDim>
			  <SubSystemName>SpeedgoatCANOpen07/Speedgoat_TPDOs/CAN Bus Communication/CANOpen Slave  Protocol Stack - CAN Bus #1 (A)/CAN RX Wrapper</SubSystemName>
			  <sigTestPoint>false</sigTestPoint>
            </signal>
			  
			  
              <signal>
              <sigName>CAN Read/p6</sigName>
              <xpcsigName>Speedgoat_TPDOs/CAN Bus Communication/CANOpen Slave  Protocol Stack - CAN Bus #1 (A)/CAN RX Wrapper/CAN Read/p6</xpcsigName>
              <sigWidth>8</sigWidth>
              <sigDim>[8, 1]</sigDim>
			  <SubSystemName>SpeedgoatCANOpen07/Speedgoat_TPDOs/CAN Bus Communication/CANOpen Slave  Protocol Stack - CAN Bus #1 (A)/CAN RX Wrapper</SubSystemName>
			  <sigTestPoint>false</sigTestPoint>
            </signal>
			  
			  
              <signal>
              <sigName>Switch</sigName>
              <xpcsigName>Speedgoat_TPDOs/CAN Bus Communication/CANOpen Slave  Protocol Stack - CAN Bus #1 (A)/CAN RX Wrapper/Switch</xpcsigName>
              <sigWidth>1</sigWidth>
              <sigDim>[1, 1]</sigDim>
			  <SubSystemName>SpeedgoatCANOpen07/Speedgoat_TPDOs/CAN Bus Communication/CANOpen Slave  Protocol Stack - CAN Bus #1 (A)/CAN RX Wrapper</SubSystemName>
			  <sigTestPoint>false</sigTestPoint>
            </signal>

		</SubSystem>
		<SubSystem>
		<Name>CAN TX Wrapper</Name>
		<xPCName>SpeedgoatCANOpen07/Speedgoat_TPDOs/CAN Bus Communication/CANOpen Slave  Protocol Stack - CAN Bus #1 (A)/CAN TX Wrapper</xPCName>
		
		
            <block>
            <blkName>Constant</blkName>
            <xpcblkName>Speedgoat_TPDOs/CAN Bus Communication/CANOpen Slave  Protocol Stack - CAN Bus #1 (A)/CAN TX Wrapper/Constant</xpcblkName>
            <SLblockPath>SpeedgoatCANOpen07/Speedgoat_TPDOs/CAN Bus Communication/CANOpen Slave  Protocol Stack - CAN Bus #1 (A)/CAN TX Wrapper/Constant</SLblockPath>
            <isSrc>[1 0 1]</isSrc>
          <parameter>
          <paramName>Value</paramName>
          <dim>[1, 1]</dim>  
		  <SubSystemName>SpeedgoatCANOpen07/Speedgoat_TPDOs/CAN Bus Communication/CANOpen Slave  Protocol Stack - CAN Bus #1 (A)/CAN TX Wrapper</SubSystemName>
          </parameter>
          </block>
            <block>
            <blkName>CAN Write</blkName>
            <xpcblkName>Speedgoat_TPDOs/CAN Bus Communication/CANOpen Slave  Protocol Stack - CAN Bus #1 (A)/CAN TX Wrapper/CAN Write</xpcblkName>
            <SLblockPath>SpeedgoatCANOpen07/Speedgoat_TPDOs/CAN Bus Communication/CANOpen Slave  Protocol Stack - CAN Bus #1 (A)/CAN TX Wrapper/CAN Write</SLblockPath>
            <isSrc>[0 4 0]</isSrc>
          <parameter>
          <paramName>P1</paramName>
          <dim>[1, 7]</dim>  
		  <SubSystemName>SpeedgoatCANOpen07/Speedgoat_TPDOs/CAN Bus Communication/CANOpen Slave  Protocol Stack - CAN Bus #1 (A)/CAN TX Wrapper</SubSystemName>
          </parameter>
          </block>
			  
			  
              <signal>
              <sigName>Constant</sigName>
              <xpcsigName>Speedgoat_TPDOs/CAN Bus Communication/CANOpen Slave  Protocol Stack - CAN Bus #1 (A)/CAN TX Wrapper/Constant</xpcsigName>
              <sigWidth>1</sigWidth>
              <sigDim>[1, 1]</sigDim>
			  <SubSystemName>SpeedgoatCANOpen07/Speedgoat_TPDOs/CAN Bus Communication/CANOpen Slave  Protocol Stack - CAN Bus #1 (A)/CAN TX Wrapper</SubSystemName>
			  <sigTestPoint>false</sigTestPoint>
            </signal>

		</SubSystem>

		
			  
			  
              <signal>
              <sigName>C Caller/p1</sigName>
              <xpcsigName>Speedgoat_TPDOs/CAN Bus Communication/CANOpen Slave  Protocol Stack - CAN Bus #1 (A)/C Caller/p1</xpcsigName>
              <sigWidth>1</sigWidth>
              <sigDim>[1, 1]</sigDim>
			  <SubSystemName>SpeedgoatCANOpen07/Speedgoat_TPDOs/CAN Bus Communication/CANOpen Slave  Protocol Stack - CAN Bus #1 (A)</SubSystemName>
			  <sigTestPoint>false</sigTestPoint>
            </signal>
			  
			  
              <signal>
              <sigName>C Caller/p2</sigName>
              <xpcsigName>Speedgoat_TPDOs/CAN Bus Communication/CANOpen Slave  Protocol Stack - CAN Bus #1 (A)/C Caller/p2</xpcsigName>
              <sigWidth>1</sigWidth>
              <sigDim>[1, 1]</sigDim>
			  <SubSystemName>SpeedgoatCANOpen07/Speedgoat_TPDOs/CAN Bus Communication/CANOpen Slave  Protocol Stack - CAN Bus #1 (A)</SubSystemName>
			  <sigTestPoint>false</sigTestPoint>
            </signal>
			  
			  
              <signal>
              <sigName>C Caller/p3</sigName>
              <xpcsigName>Speedgoat_TPDOs/CAN Bus Communication/CANOpen Slave  Protocol Stack - CAN Bus #1 (A)/C Caller/p3</xpcsigName>
              <sigWidth>8</sigWidth>
              <sigDim>[8, 1]</sigDim>
			  <SubSystemName>SpeedgoatCANOpen07/Speedgoat_TPDOs/CAN Bus Communication/CANOpen Slave  Protocol Stack - CAN Bus #1 (A)</SubSystemName>
			  <sigTestPoint>false</sigTestPoint>
            </signal>

		</SubSystem>
		<SubSystem>
		<Name>CANOpen Slave 
Protocol Stack - CAN Bus #2 (B)</Name>
		<xPCName>SpeedgoatCANOpen07/Speedgoat_TPDOs/CAN Bus Communication/CANOpen Slave  Protocol Stack - CAN Bus #2 (B)</xPCName>
				<SubSystem>
		<Name>CAN RX Wrapper</Name>
		<xPCName>SpeedgoatCANOpen07/Speedgoat_TPDOs/CAN Bus Communication/CANOpen Slave  Protocol Stack - CAN Bus #2 (B)/CAN RX Wrapper</xPCName>
		
		
            <block>
            <blkName>CAN Read</blkName>
            <xpcblkName>Speedgoat_TPDOs/CAN Bus Communication/CANOpen Slave  Protocol Stack - CAN Bus #2 (B)/CAN RX Wrapper/CAN Read</xpcblkName>
            <SLblockPath>SpeedgoatCANOpen07/Speedgoat_TPDOs/CAN Bus Communication/CANOpen Slave  Protocol Stack - CAN Bus #2 (B)/CAN RX Wrapper/CAN Read</SLblockPath>
            <isSrc>[1 0 6]</isSrc>
          <parameter>
          <paramName>P1</paramName>
          <dim>[1, 6]</dim>  
		  <SubSystemName>SpeedgoatCANOpen07/Speedgoat_TPDOs/CAN Bus Communication/CANOpen Slave  Protocol Stack - CAN Bus #2 (B)/CAN RX Wrapper</SubSystemName>
          </parameter>
          </block>
            <block>
            <blkName>Switch</blkName>
            <xpcblkName>Speedgoat_TPDOs/CAN Bus Communication/CANOpen Slave  Protocol Stack - CAN Bus #2 (B)/CAN RX Wrapper/Switch</xpcblkName>
            <SLblockPath>SpeedgoatCANOpen07/Speedgoat_TPDOs/CAN Bus Communication/CANOpen Slave  Protocol Stack - CAN Bus #2 (B)/CAN RX Wrapper/Switch</SLblockPath>
            <isSrc>[0 3 1]</isSrc>
          <parameter>
          <paramName>Threshold</paramName>
          <dim>[1, 1]</dim>  
		  <SubSystemName>SpeedgoatCANOpen07/Speedgoat_TPDOs/CAN Bus Communication/CANOpen Slave  Protocol Stack - CAN Bus #2 (B)/CAN RX Wrapper</SubSystemName>
          </parameter>
          </block>
			  
			  
              <signal>
              <sigName>CAN Read/p1</sigName>
              <xpcsigName>Speedgoat_TPDOs/CAN Bus Communication/CANOpen Slave  Protocol Stack - CAN Bus #2 (B)/CAN RX Wrapper/CAN Read/p1</xpcsigName>
              <sigWidth>1</sigWidth>
              <sigDim>[1, 1]</sigDim>
			  <SubSystemName>SpeedgoatCANOpen07/Speedgoat_TPDOs/CAN Bus Communication/CANOpen Slave  Protocol Stack - CAN Bus #2 (B)/CAN RX Wrapper</SubSystemName>
			  <sigTestPoint>false</sigTestPoint>
            </signal>
			  
			  
              <signal>
              <sigName>CAN Read/p2</sigName>
              <xpcsigName>Speedgoat_TPDOs/CAN Bus Communication/CANOpen Slave  Protocol Stack - CAN Bus #2 (B)/CAN RX Wrapper/CAN Read/p2</xpcsigName>
              <sigWidth>1</sigWidth>
              <sigDim>[1, 1]</sigDim>
			  <SubSystemName>SpeedgoatCANOpen07/Speedgoat_TPDOs/CAN Bus Communication/CANOpen Slave  Protocol Stack - CAN Bus #2 (B)/CAN RX Wrapper</SubSystemName>
			  <sigTestPoint>false</sigTestPoint>
            </signal>
			  
			  
              <signal>
              <sigName>CAN Read/p3</sigName>
              <xpcsigName>Speedgoat_TPDOs/CAN Bus Communication/CANOpen Slave  Protocol Stack - CAN Bus #2 (B)/CAN RX Wrapper/CAN Read/p3</xpcsigName>
              <sigWidth>1</sigWidth>
              <sigDim>[1, 1]</sigDim>
			  <SubSystemName>SpeedgoatCANOpen07/Speedgoat_TPDOs/CAN Bus Communication/CANOpen Slave  Protocol Stack - CAN Bus #2 (B)/CAN RX Wrapper</SubSystemName>
			  <sigTestPoint>false</sigTestPoint>
            </signal>
			  
			  
              <signal>
              <sigName>CAN Read/p4</sigName>
              <xpcsigName>Speedgoat_TPDOs/CAN Bus Communication/CANOpen Slave  Protocol Stack - CAN Bus #2 (B)/CAN RX Wrapper/CAN Read/p4</xpcsigName>
              <sigWidth>1</sigWidth>
              <sigDim>[1, 1]</sigDim>
			  <SubSystemName>SpeedgoatCANOpen07/Speedgoat_TPDOs/CAN Bus Communication/CANOpen Slave  Protocol Stack - CAN Bus #2 (B)/CAN RX Wrapper</SubSystemName>
			  <sigTestPoint>false</sigTestPoint>
            </signal>
			  
			  
              <signal>
              <sigName>CAN Read/p5</sigName>
              <xpcsigName>Speedgoat_TPDOs/CAN Bus Communication/CANOpen Slave  Protocol Stack - CAN Bus #2 (B)/CAN RX Wrapper/CAN Read/p5</xpcsigName>
              <sigWidth>1</sigWidth>
              <sigDim>[1, 1]</sigDim>
			  <SubSystemName>SpeedgoatCANOpen07/Speedgoat_TPDOs/CAN Bus Communication/CANOpen Slave  Protocol Stack - CAN Bus #2 (B)/CAN RX Wrapper</SubSystemName>
			  <sigTestPoint>false</sigTestPoint>
            </signal>
			  
			  
              <signal>
              <sigName>CAN Read/p6</sigName>
              <xpcsigName>Speedgoat_TPDOs/CAN Bus Communication/CANOpen Slave  Protocol Stack - CAN Bus #2 (B)/CAN RX Wrapper/CAN Read/p6</xpcsigName>
              <sigWidth>8</sigWidth>
              <sigDim>[8, 1]</sigDim>
			  <SubSystemName>SpeedgoatCANOpen07/Speedgoat_TPDOs/CAN Bus Communication/CANOpen Slave  Protocol Stack - CAN Bus #2 (B)/CAN RX Wrapper</SubSystemName>
			  <sigTestPoint>false</sigTestPoint>
            </signal>
			  
			  
              <signal>
              <sigName>Switch</sigName>
              <xpcsigName>Speedgoat_TPDOs/CAN Bus Communication/CANOpen Slave  Protocol Stack - CAN Bus #2 (B)/CAN RX Wrapper/Switch</xpcsigName>
              <sigWidth>1</sigWidth>
              <sigDim>[1, 1]</sigDim>
			  <SubSystemName>SpeedgoatCANOpen07/Speedgoat_TPDOs/CAN Bus Communication/CANOpen Slave  Protocol Stack - CAN Bus #2 (B)/CAN RX Wrapper</SubSystemName>
			  <sigTestPoint>false</sigTestPoint>
            </signal>

		</SubSystem>
		<SubSystem>
		<Name>CAN TX Wrapper</Name>
		<xPCName>SpeedgoatCANOpen07/Speedgoat_TPDOs/CAN Bus Communication/CANOpen Slave  Protocol Stack - CAN Bus #2 (B)/CAN TX Wrapper</xPCName>
		
		
            <block>
            <blkName>Constant</blkName>
            <xpcblkName>Speedgoat_TPDOs/CAN Bus Communication/CANOpen Slave  Protocol Stack - CAN Bus #2 (B)/CAN TX Wrapper/Constant</xpcblkName>
            <SLblockPath>SpeedgoatCANOpen07/Speedgoat_TPDOs/CAN Bus Communication/CANOpen Slave  Protocol Stack - CAN Bus #2 (B)/CAN TX Wrapper/Constant</SLblockPath>
            <isSrc>[1 0 1]</isSrc>
          <parameter>
          <paramName>Value</paramName>
          <dim>[1, 1]</dim>  
		  <SubSystemName>SpeedgoatCANOpen07/Speedgoat_TPDOs/CAN Bus Communication/CANOpen Slave  Protocol Stack - CAN Bus #2 (B)/CAN TX Wrapper</SubSystemName>
          </parameter>
          </block>
            <block>
            <blkName>CAN Write</blkName>
            <xpcblkName>Speedgoat_TPDOs/CAN Bus Communication/CANOpen Slave  Protocol Stack - CAN Bus #2 (B)/CAN TX Wrapper/CAN Write</xpcblkName>
            <SLblockPath>SpeedgoatCANOpen07/Speedgoat_TPDOs/CAN Bus Communication/CANOpen Slave  Protocol Stack - CAN Bus #2 (B)/CAN TX Wrapper/CAN Write</SLblockPath>
            <isSrc>[0 4 0]</isSrc>
          <parameter>
          <paramName>P1</paramName>
          <dim>[1, 7]</dim>  
		  <SubSystemName>SpeedgoatCANOpen07/Speedgoat_TPDOs/CAN Bus Communication/CANOpen Slave  Protocol Stack - CAN Bus #2 (B)/CAN TX Wrapper</SubSystemName>
          </parameter>
          </block>
			  
			  
              <signal>
              <sigName>Constant</sigName>
              <xpcsigName>Speedgoat_TPDOs/CAN Bus Communication/CANOpen Slave  Protocol Stack - CAN Bus #2 (B)/CAN TX Wrapper/Constant</xpcsigName>
              <sigWidth>1</sigWidth>
              <sigDim>[1, 1]</sigDim>
			  <SubSystemName>SpeedgoatCANOpen07/Speedgoat_TPDOs/CAN Bus Communication/CANOpen Slave  Protocol Stack - CAN Bus #2 (B)/CAN TX Wrapper</SubSystemName>
			  <sigTestPoint>false</sigTestPoint>
            </signal>

		</SubSystem>

		
			  
			  
              <signal>
              <sigName>C Caller/p1</sigName>
              <xpcsigName>Speedgoat_TPDOs/CAN Bus Communication/CANOpen Slave  Protocol Stack - CAN Bus #2 (B)/C Caller/p1</xpcsigName>
              <sigWidth>1</sigWidth>
              <sigDim>[1, 1]</sigDim>
			  <SubSystemName>SpeedgoatCANOpen07/Speedgoat_TPDOs/CAN Bus Communication/CANOpen Slave  Protocol Stack - CAN Bus #2 (B)</SubSystemName>
			  <sigTestPoint>false</sigTestPoint>
            </signal>
			  
			  
              <signal>
              <sigName>C Caller/p2</sigName>
              <xpcsigName>Speedgoat_TPDOs/CAN Bus Communication/CANOpen Slave  Protocol Stack - CAN Bus #2 (B)/C Caller/p2</xpcsigName>
              <sigWidth>1</sigWidth>
              <sigDim>[1, 1]</sigDim>
			  <SubSystemName>SpeedgoatCANOpen07/Speedgoat_TPDOs/CAN Bus Communication/CANOpen Slave  Protocol Stack - CAN Bus #2 (B)</SubSystemName>
			  <sigTestPoint>false</sigTestPoint>
            </signal>
			  
			  
              <signal>
              <sigName>C Caller/p3</sigName>
              <xpcsigName>Speedgoat_TPDOs/CAN Bus Communication/CANOpen Slave  Protocol Stack - CAN Bus #2 (B)/C Caller/p3</xpcsigName>
              <sigWidth>8</sigWidth>
              <sigDim>[8, 1]</sigDim>
			  <SubSystemName>SpeedgoatCANOpen07/Speedgoat_TPDOs/CAN Bus Communication/CANOpen Slave  Protocol Stack - CAN Bus #2 (B)</SubSystemName>
			  <sigTestPoint>false</sigTestPoint>
            </signal>

		</SubSystem>

		
            <block>
            <blkName>CAN Setup </blkName>
            <xpcblkName>Speedgoat_TPDOs/CAN Bus Communication/CAN Setup </xpcblkName>
            <SLblockPath>SpeedgoatCANOpen07/Speedgoat_TPDOs/CAN Bus Communication/CAN Setup </SLblockPath>
            <isSrc>[0 0 0]</isSrc>
          <parameter>
          <paramName>P1</paramName>
          <dim>[1, 40]</dim>  
		  <SubSystemName>SpeedgoatCANOpen07/Speedgoat_TPDOs/CAN Bus Communication</SubSystemName>
          </parameter>
          <parameter>
          <paramName>P2</paramName>
          <dim>[1, 1]</dim>  
		  <SubSystemName>SpeedgoatCANOpen07/Speedgoat_TPDOs/CAN Bus Communication</SubSystemName>
          </parameter>
          <parameter>
          <paramName>P3</paramName>
          <dim>[1, 1]</dim>  
		  <SubSystemName>SpeedgoatCANOpen07/Speedgoat_TPDOs/CAN Bus Communication</SubSystemName>
          </parameter>
          </block>

		</SubSystem>

		

		</SubSystem>
		<SubSystem>
		<Name>Trike Application Layer</Name>
		<xPCName>SpeedgoatCANOpen07/Trike Application Layer</xPCName>
				<SubSystem>
		<Name>APT BusVoltage</Name>
		<xPCName>SpeedgoatCANOpen07/Trike Application Layer/APT BusVoltage</xPCName>
		
		

		</SubSystem>
		<SubSystem>
		<Name>PedalPosition</Name>
		<xPCName>SpeedgoatCANOpen07/Trike Application Layer/PedalPosition</xPCName>
		
		

		</SubSystem>
		<SubSystem>
		<Name>PedalPosition1</Name>
		<xPCName>SpeedgoatCANOpen07/Trike Application Layer/PedalPosition1</xPCName>
		
		

		</SubSystem>
		<SubSystem>
		<Name>PedalPosition2</Name>
		<xPCName>SpeedgoatCANOpen07/Trike Application Layer/PedalPosition2</xPCName>
		
		

		</SubSystem>
		<SubSystem>
		<Name>PedalPosition3</Name>
		<xPCName>SpeedgoatCANOpen07/Trike Application Layer/PedalPosition3</xPCName>
		
		

		</SubSystem>
		<SubSystem>
		<Name>PedalPosition4</Name>
		<xPCName>SpeedgoatCANOpen07/Trike Application Layer/PedalPosition4</xPCName>
		
		

		</SubSystem>
		<SubSystem>
		<Name>PedalPosition5</Name>
		<xPCName>SpeedgoatCANOpen07/Trike Application Layer/PedalPosition5</xPCName>
		
		

		</SubSystem>
		<SubSystem>
		<Name>PedalPosition6</Name>
		<xPCName>SpeedgoatCANOpen07/Trike Application Layer/PedalPosition6</xPCName>
		
		

		</SubSystem>
		<SubSystem>
		<Name>PedalPosition7</Name>
		<xPCName>SpeedgoatCANOpen07/Trike Application Layer/PedalPosition7</xPCName>
		
		

		</SubSystem>
		<SubSystem>
		<Name>HeartBeatgenerator</Name>
		<xPCName>SpeedgoatCANOpen07/Trike Application Layer/HeartBeatgenerator</xPCName>
		
		

		</SubSystem>
		<SubSystem>
		<Name>MATLAB Function</Name>
		<xPCName>SpeedgoatCANOpen07/Trike Application Layer/MATLAB Function</xPCName>
		
		

		</SubSystem>
		<SubSystem>
		<Name>MATLAB Function6</Name>
		<xPCName>SpeedgoatCANOpen07/Trike Application Layer/MATLAB Function6</xPCName>
		
		

		</SubSystem>
		<SubSystem>
		<Name>MATLAB Function7</Name>
		<xPCName>SpeedgoatCANOpen07/Trike Application Layer/MATLAB Function7</xPCName>
		
		

		</SubSystem>
		<SubSystem>
		<Name>Set_0_pos_homing</Name>
		<xPCName>SpeedgoatCANOpen07/Trike Application Layer/Set_0_pos_homing</xPCName>
		
		

		</SubSystem>

		
            <block>
            <blkName>Constant1</blkName>
            <xpcblkName>Trike Application Layer/Constant1</xpcblkName>
            <SLblockPath>SpeedgoatCANOpen07/Trike Application Layer/Constant1</SLblockPath>
            <isSrc>[1 0 1]</isSrc>
          <parameter>
          <paramName>Value</paramName>
          <dim>[1, 1]</dim>  
		  <SubSystemName>SpeedgoatCANOpen07/Trike Application Layer</SubSystemName>
          </parameter>
          </block>
            <block>
            <blkName>Constant2</blkName>
            <xpcblkName>Trike Application Layer/Constant2</xpcblkName>
            <SLblockPath>SpeedgoatCANOpen07/Trike Application Layer/Constant2</SLblockPath>
            <isSrc>[1 0 1]</isSrc>
          <parameter>
          <paramName>Value</paramName>
          <dim>[1, 1]</dim>  
		  <SubSystemName>SpeedgoatCANOpen07/Trike Application Layer</SubSystemName>
          </parameter>
          </block>
            <block>
            <blkName>Constant3</blkName>
            <xpcblkName>Trike Application Layer/Constant3</xpcblkName>
            <SLblockPath>SpeedgoatCANOpen07/Trike Application Layer/Constant3</SLblockPath>
            <isSrc>[1 0 1]</isSrc>
          <parameter>
          <paramName>Value</paramName>
          <dim>[1, 1]</dim>  
		  <SubSystemName>SpeedgoatCANOpen07/Trike Application Layer</SubSystemName>
          </parameter>
          </block>
            <block>
            <blkName>Gain</blkName>
            <xpcblkName>Trike Application Layer/Gain</xpcblkName>
            <SLblockPath>SpeedgoatCANOpen07/Trike Application Layer/Gain</SLblockPath>
            <isSrc>[0 1 1]</isSrc>
          <parameter>
          <paramName>Gain</paramName>
          <dim>[1, 1]</dim>  
		  <SubSystemName>SpeedgoatCANOpen07/Trike Application Layer</SubSystemName>
          </parameter>
          </block>
            <block>
            <blkName>Gain1</blkName>
            <xpcblkName>Trike Application Layer/Gain1</xpcblkName>
            <SLblockPath>SpeedgoatCANOpen07/Trike Application Layer/Gain1</SLblockPath>
            <isSrc>[0 1 1]</isSrc>
          <parameter>
          <paramName>Gain</paramName>
          <dim>[1, 1]</dim>  
		  <SubSystemName>SpeedgoatCANOpen07/Trike Application Layer</SubSystemName>
          </parameter>
          </block>
            <block>
            <blkName>Gain3</blkName>
            <xpcblkName>Trike Application Layer/Gain3</xpcblkName>
            <SLblockPath>SpeedgoatCANOpen07/Trike Application Layer/Gain3</SLblockPath>
            <isSrc>[0 1 1]</isSrc>
          <parameter>
          <paramName>Gain</paramName>
          <dim>[1, 1]</dim>  
		  <SubSystemName>SpeedgoatCANOpen07/Trike Application Layer</SubSystemName>
          </parameter>
          </block>
            <block>
            <blkName>Gain6</blkName>
            <xpcblkName>Trike Application Layer/Gain6</xpcblkName>
            <SLblockPath>SpeedgoatCANOpen07/Trike Application Layer/Gain6</SLblockPath>
            <isSrc>[0 1 1]</isSrc>
          <parameter>
          <paramName>Gain</paramName>
          <dim>[1, 1]</dim>  
		  <SubSystemName>SpeedgoatCANOpen07/Trike Application Layer</SubSystemName>
          </parameter>
          </block>
			  
			  
              <signal>
              <sigName>HeartBeatgenerator</sigName>
              <xpcsigName>Trike Application Layer/HeartBeatgenerator</xpcsigName>
              <sigWidth>1</sigWidth>
              <sigDim>[1, 1]</sigDim>
			  <SubSystemName>SpeedgoatCANOpen07/Trike Application Layer</SubSystemName>
			  <sigTestPoint>false</sigTestPoint>
            </signal>
			  
			  
              <signal>
              <sigName>MATLAB Function</sigName>
              <xpcsigName>Trike Application Layer/MATLAB Function</xpcsigName>
              <sigWidth>1</sigWidth>
              <sigDim>[1, 1]</sigDim>
			  <SubSystemName>SpeedgoatCANOpen07/Trike Application Layer</SubSystemName>
			  <sigTestPoint>false</sigTestPoint>
            </signal>
			  
			  
              <signal>
              <sigName>MATLAB Function6</sigName>
              <xpcsigName>Trike Application Layer/MATLAB Function6</xpcsigName>
              <sigWidth>1</sigWidth>
              <sigDim>[1, 1]</sigDim>
			  <SubSystemName>SpeedgoatCANOpen07/Trike Application Layer</SubSystemName>
			  <sigTestPoint>false</sigTestPoint>
            </signal>
			  
			  
              <signal>
              <sigName>MATLAB Function7</sigName>
              <xpcsigName>Trike Application Layer/MATLAB Function7</xpcsigName>
              <sigWidth>1</sigWidth>
              <sigDim>[1, 1]</sigDim>
			  <SubSystemName>SpeedgoatCANOpen07/Trike Application Layer</SubSystemName>
			  <sigTestPoint>false</sigTestPoint>
            </signal>
			  
			  
              <signal>
              <sigName>Set_0_pos_homing/p1</sigName>
              <xpcsigName>Trike Application Layer/Set_0_pos_homing/p1</xpcsigName>
              <sigWidth>1</sigWidth>
              <sigDim>[1, 1]</sigDim>
			  <SubSystemName>SpeedgoatCANOpen07/Trike Application Layer</SubSystemName>
                <sigLabel>ctrl_word</sigLabel>
			  <sigTestPoint>false</sigTestPoint>
            </signal>
			  
			  
              <signal>
              <sigName>Set_0_pos_homing/p2</sigName>
              <xpcsigName>Trike Application Layer/Set_0_pos_homing/p2</xpcsigName>
              <sigWidth>1</sigWidth>
              <sigDim>[1, 1]</sigDim>
			  <SubSystemName>SpeedgoatCANOpen07/Trike Application Layer</SubSystemName>
                <sigLabel>ctrl_op_mode</sigLabel>
			  <sigTestPoint>false</sigTestPoint>
            </signal>
			  
			  
              <signal>
              <sigName>Set_0_pos_homing/p3</sigName>
              <xpcsigName>Trike Application Layer/Set_0_pos_homing/p3</xpcsigName>
              <sigWidth>1</sigWidth>
              <sigDim>[1, 1]</sigDim>
			  <SubSystemName>SpeedgoatCANOpen07/Trike Application Layer</SubSystemName>
                <sigLabel>ctrl_position</sigLabel>
			  <sigTestPoint>false</sigTestPoint>
            </signal>
			  
			  
              <signal>
              <sigName>Abs</sigName>
              <xpcsigName>Trike Application Layer/Abs</xpcsigName>
              <sigWidth>1</sigWidth>
              <sigDim>[1, 1]</sigDim>
			  <SubSystemName>SpeedgoatCANOpen07/Trike Application Layer</SubSystemName>
			  <sigTestPoint>false</sigTestPoint>
            </signal>
			  
			  
              <signal>
              <sigName>Data Type Conversion</sigName>
              <xpcsigName>Trike Application Layer/Data Type Conversion</xpcsigName>
              <sigWidth>1</sigWidth>
              <sigDim>[1, 1]</sigDim>
			  <SubSystemName>SpeedgoatCANOpen07/Trike Application Layer</SubSystemName>
                <sigLabel>APT_TPDO_ControlWord</sigLabel>
			  <sigTestPoint>false</sigTestPoint>
            </signal>
			  
			  
              <signal>
              <sigName>Data Type Conversion1</sigName>
              <xpcsigName>Trike Application Layer/Data Type Conversion1</xpcsigName>
              <sigWidth>1</sigWidth>
              <sigDim>[1, 1]</sigDim>
			  <SubSystemName>SpeedgoatCANOpen07/Trike Application Layer</SubSystemName>
                <sigLabel>APT_TPDO_PedalPosition</sigLabel>
			  <sigTestPoint>false</sigTestPoint>
            </signal>
			  
			  
              <signal>
              <sigName>Data Type Conversion10</sigName>
              <xpcsigName>Trike Application Layer/Data Type Conversion10</xpcsigName>
              <sigWidth>1</sigWidth>
              <sigDim>[1, 1]</sigDim>
			  <SubSystemName>SpeedgoatCANOpen07/Trike Application Layer</SubSystemName>
                <sigLabel>sts_op_mode</sigLabel>
			  <sigTestPoint>false</sigTestPoint>
            </signal>
			  
			  
              <signal>
              <sigName>Data Type Conversion11</sigName>
              <xpcsigName>Trike Application Layer/Data Type Conversion11</xpcsigName>
              <sigWidth>1</sigWidth>
              <sigDim>[1, 1]</sigDim>
			  <SubSystemName>SpeedgoatCANOpen07/Trike Application Layer</SubSystemName>
                <sigLabel>target_pos</sigLabel>
			  <sigTestPoint>false</sigTestPoint>
            </signal>
			  
			  
              <signal>
              <sigName>Data Type Conversion12</sigName>
              <xpcsigName>Trike Application Layer/Data Type Conversion12</xpcsigName>
              <sigWidth>1</sigWidth>
              <sigDim>[1, 1]</sigDim>
			  <SubSystemName>SpeedgoatCANOpen07/Trike Application Layer</SubSystemName>
                <sigLabel>poweron</sigLabel>
			  <sigTestPoint>false</sigTestPoint>
            </signal>
			  
			  
              <signal>
              <sigName>Data Type Conversion13</sigName>
              <xpcsigName>Trike Application Layer/Data Type Conversion13</xpcsigName>
              <sigWidth>1</sigWidth>
              <sigDim>[1, 1]</sigDim>
			  <SubSystemName>SpeedgoatCANOpen07/Trike Application Layer</SubSystemName>
                <sigLabel>set_homing</sigLabel>
			  <sigTestPoint>false</sigTestPoint>
            </signal>
			  
			  
              <signal>
              <sigName>Data Type Conversion2</sigName>
              <xpcsigName>Trike Application Layer/Data Type Conversion2</xpcsigName>
              <sigWidth>1</sigWidth>
              <sigDim>[1, 1]</sigDim>
			  <SubSystemName>SpeedgoatCANOpen07/Trike Application Layer</SubSystemName>
                <sigLabel>APT_TPDO_Heartbeat</sigLabel>
			  <sigTestPoint>false</sigTestPoint>
            </signal>
			  
			  
              <signal>
              <sigName>Data Type Conversion3</sigName>
              <xpcsigName>Trike Application Layer/Data Type Conversion3</xpcsigName>
              <sigWidth>1</sigWidth>
              <sigDim>[1, 1]</sigDim>
			  <SubSystemName>SpeedgoatCANOpen07/Trike Application Layer</SubSystemName>
                <sigLabel>DunkA_TPDO_ControlWord</sigLabel>
			  <sigTestPoint>false</sigTestPoint>
            </signal>
			  
			  
              <signal>
              <sigName>Data Type Conversion4</sigName>
              <xpcsigName>Trike Application Layer/Data Type Conversion4</xpcsigName>
              <sigWidth>1</sigWidth>
              <sigDim>[1, 1]</sigDim>
			  <SubSystemName>SpeedgoatCANOpen07/Trike Application Layer</SubSystemName>
                <sigLabel>DunkA_TPDO_TargetVelocity</sigLabel>
			  <sigTestPoint>false</sigTestPoint>
            </signal>
			  
			  
              <signal>
              <sigName>Data Type Conversion5</sigName>
              <xpcsigName>Trike Application Layer/Data Type Conversion5</xpcsigName>
              <sigWidth>1</sigWidth>
              <sigDim>[1, 1]</sigDim>
			  <SubSystemName>SpeedgoatCANOpen07/Trike Application Layer</SubSystemName>
                <sigLabel>DunkA_TPDO_BrakeControl</sigLabel>
			  <sigTestPoint>false</sigTestPoint>
            </signal>
			  
			  
              <signal>
              <sigName>Data Type Conversion6</sigName>
              <xpcsigName>Trike Application Layer/Data Type Conversion6</xpcsigName>
              <sigWidth>1</sigWidth>
              <sigDim>[1, 1]</sigDim>
			  <SubSystemName>SpeedgoatCANOpen07/Trike Application Layer</SubSystemName>
                <sigLabel>DunkA_TPDO_OperationMode</sigLabel>
			  <sigTestPoint>false</sigTestPoint>
            </signal>
			  
			  
              <signal>
              <sigName>Data Type Conversion7</sigName>
              <xpcsigName>Trike Application Layer/Data Type Conversion7</xpcsigName>
              <sigWidth>1</sigWidth>
              <sigDim>[1, 1]</sigDim>
			  <SubSystemName>SpeedgoatCANOpen07/Trike Application Layer</SubSystemName>
                <sigLabel>DunkA_TPDO_TargetTorque</sigLabel>
			  <sigTestPoint>false</sigTestPoint>
            </signal>
			  
			  
              <signal>
              <sigName>Data Type Conversion8</sigName>
              <xpcsigName>Trike Application Layer/Data Type Conversion8</xpcsigName>
              <sigWidth>1</sigWidth>
              <sigDim>[1, 1]</sigDim>
			  <SubSystemName>SpeedgoatCANOpen07/Trike Application Layer</SubSystemName>
                <sigLabel>DunkA_TPDO_TargetPosition</sigLabel>
			  <sigTestPoint>false</sigTestPoint>
            </signal>
			  
			  
              <signal>
              <sigName>Data Type Conversion9</sigName>
              <xpcsigName>Trike Application Layer/Data Type Conversion9</xpcsigName>
              <sigWidth>1</sigWidth>
              <sigDim>[1, 1]</sigDim>
			  <SubSystemName>SpeedgoatCANOpen07/Trike Application Layer</SubSystemName>
                <sigLabel>sts_word</sigLabel>
			  <sigTestPoint>false</sigTestPoint>
            </signal>
			  
			  
              <signal>
              <sigName>Gain</sigName>
              <xpcsigName>Trike Application Layer/Gain</xpcsigName>
              <sigWidth>1</sigWidth>
              <sigDim>[1, 1]</sigDim>
			  <SubSystemName>SpeedgoatCANOpen07/Trike Application Layer</SubSystemName>
			  <sigTestPoint>false</sigTestPoint>
            </signal>
			  
			  
              <signal>
              <sigName>Gain1</sigName>
              <xpcsigName>Trike Application Layer/Gain1</xpcsigName>
              <sigWidth>1</sigWidth>
              <sigDim>[1, 1]</sigDim>
			  <SubSystemName>SpeedgoatCANOpen07/Trike Application Layer</SubSystemName>
			  <sigTestPoint>false</sigTestPoint>
            </signal>
			  
			  
              <signal>
              <sigName>Gain3</sigName>
              <xpcsigName>Trike Application Layer/Gain3</xpcsigName>
              <sigWidth>1</sigWidth>
              <sigDim>[1, 1]</sigDim>
			  <SubSystemName>SpeedgoatCANOpen07/Trike Application Layer</SubSystemName>
			  <sigTestPoint>false</sigTestPoint>
            </signal>
			  
			  
              <signal>
              <sigName>Gain6</sigName>
              <xpcsigName>Trike Application Layer/Gain6</xpcsigName>
              <sigWidth>1</sigWidth>
              <sigDim>[1, 1]</sigDim>
			  <SubSystemName>SpeedgoatCANOpen07/Trike Application Layer</SubSystemName>
			  <sigTestPoint>false</sigTestPoint>
            </signal>

		</SubSystem>

      

</Root>